pytest_matchers/__init__.py
pytest_matchers/asserts/__init__.py
pytest_matchers/asserts/asserts.py
pytest_matchers/asserts/comparer.py
pytest_matchers/asserts/comparers/__init__.py
pytest_matchers/asserts/comparers/base.py
pytest_matchers/asserts/comparers/dict.py
pytest_matchers/asserts/comparers/list.py
pytest_matchers/asserts/comparers/set.py
pytest_matchers/main.py
pytest_matchers/matchers/__init__.py
pytest_matchers/matchers/after_applying.py
pytest_matchers/matchers/and_matcher.py
pytest_matchers/matchers/anything.py
pytest_matchers/matchers/base.py
pytest_matchers/matchers/between.py
pytest_matchers/matchers/case.py
pytest_matchers/matchers/contains.py
pytest_matchers/matchers/datetime.py
pytest_matchers/matchers/datetime_string.py
pytest_matchers/matchers/dict.py
pytest_matchers/matchers/different_value.py
pytest_matchers/matchers/ends_with.py
pytest_matchers/matchers/eq.py
pytest_matchers/matchers/exception.py
pytest_matchers/matchers/has_attribute.py
pytest_matchers/matchers/if_matcher.py
pytest_matchers/matchers/is_instance.py
pytest_matchers/matchers/json.py
pytest_matchers/matchers/length.py
pytest_matchers/matchers/list.py
pytest_matchers/matchers/matcher_factory.py
pytest_matchers/matchers/not_matcher.py
pytest_matchers/matchers/number.py
pytest_matchers/matchers/or_matcher.py
pytest_matchers/matchers/pydantic/__init__.py
pytest_matchers/matchers/same_value.py
pytest_matchers/matchers/starts_with.py
pytest_matchers/matchers/strict_dict.py
pytest_matchers/matchers/string.py
pytest_matchers/matchers/timestamp.py
pytest_matchers/matchers/uuid.py
pytest_matchers/plugin.py
pytest_matchers/pydantic/__init__.py
pytest_matchers/pydantic/main.py
pytest_matchers/pydantic/matchers/__init__.py
pytest_matchers/pydantic/matchers/pydantic_model.py
pytest_matchers/utils/__init__.py
pytest_matchers/utils/matcher_detector.py
pytest_matchers/utils/matcher_utils.py
pytest_matchers/utils/repr_utils.py
pytest_matchers/utils/warn.py
pytest_matchers-0.3.5.dist-info/METADATA
pytest_matchers-0.3.5.dist-info/WHEEL
pytest_matchers-0.3.5.dist-info/entry_points.txt
pytest_matchers-0.3.5.dist-info/licenses/LICENSE.txt
pytest_matchers-0.3.5.dist-info/RECORD
