Metadata-Version: 2.4
Name: pytest-matchers
Version: 0.3.5
Summary: Matchers for pytest
License-Expression: MIT
License-File: LICENSE.txt
Author: Martín Gotelli Ferenaz
Author-email: martingotelliferenaz@gmail.com
Requires-Python: >=3.10,<4.0
Classifier: Programming Language :: Python :: 3
Classifier: Programming Language :: Python :: 3.10
Classifier: Programming Language :: Python :: 3.11
Classifier: Programming Language :: Python :: 3.12
Classifier: Programming Language :: Python :: 3.13
Classifier: Programming Language :: Python :: 3.14
Provides-Extra: pydantic
Requires-Dist: pydantic (>=1.0,<3.0) ; extra == "pydantic"
Requires-Dist: pytest (>=7.0,<10.0)
